{
  "parent": "builtin/entity",
  "credit": "Made with Blockbench",
  "texture_size": [
    80,
    80
  ],
  "display": {
    "thirdperson_righthand": {
      "rotation": [ 0, 60, 0 ],
      "translation": [ 0, 0, 1]
    },
    "thirdperson_lefthand": {
      "rotation": [ 0, 60, 0 ],
      "translation": [ 0, 0, 1]
    },
    "firstperson_righthand": {
      "rotation": [ 0, -90, 30 ],
      "translation": [ 0, -3, 0]
    },
    "firstperson_lefthand": {
      "rotation": [ 0, 90, -30 ],
      "translation": [ 0, -3, 0]
    },
    "gui": {
      "rotation": [ 15, 0, -35 ],
      "translation": [ -5, -7, 0 ],
      "scale": [ 0.6, 0.6, 0.6 ]
    },
    "fixed": {
      "scale": [ 0.5, 0.5, 0.5],
      "translation": [ -2, 4, -5]
    },
    "ground": {
      "rotation": [ 0, 0, 0 ],
      "translation": [ 4, 4, 2],
      "scale":[ 0.25, 0.25, 0.25]
    }
  },
  "groups": [
    {
      "name": "pole",
      "origin": [0, 24, 0],
      "color": 0,
      "shade": false,
      "children": [0, 1, 2]
    }
  ]
}